steer_materials/Base.py
steer_materials/__init__.py
steer_materials-0.1.17.dist-info/METADATA
steer_materials-0.1.17.dist-info/WHEEL
steer_materials-0.1.17.dist-info/top_level.txt
steer_materials-0.1.17.dist-info/RECORD
