Metadata-Version: 2.4
Name: steer-materials
Version: 0.1.17
Summary: Modelling energy storage from cell to site - STEER OpenCell Design
Author-email: Nicholas Siemons <nsiemons@stanford.edu>
Maintainer-email: Nicholas Siemons <nsiemons@stanford.edu>
License: MIT
Project-URL: Homepage, https://github.com/stanford-developers/steer-materials/
Project-URL: Repository, https://github.com/stanford-developers/steer-materials/
Project-URL: Bug Tracker, https://github.com/stanford-developers/steer-materials/issues
Keywords: battery,materials,simulation,electrochemistry,energy-storage
Classifier: Development Status :: 3 - Alpha
Classifier: Intended Audience :: Developers
Classifier: Intended Audience :: Science/Research
Classifier: License :: OSI Approved :: MIT License
Classifier: Programming Language :: Python :: 3
Classifier: Programming Language :: Python :: 3.10
Classifier: Programming Language :: Python :: 3.11
Classifier: Programming Language :: Python :: 3.12
Classifier: Operating System :: OS Independent
Classifier: Topic :: Scientific/Engineering
Classifier: Topic :: Software Development :: Libraries :: Python Modules
Requires-Python: >=3.10
Requires-Dist: steer-core==0.1.27
Provides-Extra: dev
Requires-Dist: pytest; extra == "dev"
Requires-Dist: pytest-cov; extra == "dev"
Requires-Dist: black; extra == "dev"
Requires-Dist: flake8; extra == "dev"
Requires-Dist: mypy; extra == "dev"
Requires-Dist: build; extra == "dev"
Requires-Dist: twine; extra == "dev"
Provides-Extra: test
Requires-Dist: pytest; extra == "test"
Requires-Dist: pytest-cov; extra == "test"
